open_worm_analysis_toolbox/__init__.py
open_worm_analysis_toolbox/config.py
open_worm_analysis_toolbox/user_config.py
open_worm_analysis_toolbox/utils.py
open_worm_analysis_toolbox/version.py
open_worm_analysis_toolbox/features/__init__.py
open_worm_analysis_toolbox/features/events.py
open_worm_analysis_toolbox/features/feature_manipulations.py
open_worm_analysis_toolbox/features/feature_processing_options.py
open_worm_analysis_toolbox/features/generic_features.py
open_worm_analysis_toolbox/features/locomotion_bends.py
open_worm_analysis_toolbox/features/locomotion_features.py
open_worm_analysis_toolbox/features/locomotion_turns.py
open_worm_analysis_toolbox/features/morphology_features.py
open_worm_analysis_toolbox/features/path_features.py
open_worm_analysis_toolbox/features/posture_features.py
open_worm_analysis_toolbox/features/velocity.py
open_worm_analysis_toolbox/features/worm_features.py
open_worm_analysis_toolbox/features/feature_metadata/__init__.py
open_worm_analysis_toolbox/prefeatures/__init__.py
open_worm_analysis_toolbox/prefeatures/basic_worm.py
open_worm_analysis_toolbox/prefeatures/normalized_worm.py
open_worm_analysis_toolbox/prefeatures/pre_features.py
open_worm_analysis_toolbox/prefeatures/pre_features_helpers.py
open_worm_analysis_toolbox/prefeatures/skeleton_calculator1.py
open_worm_analysis_toolbox/prefeatures/video_info.py
open_worm_analysis_toolbox/prefeatures/worm_plotter.py
open_worm_analysis_toolbox/statistics/__init__.py
open_worm_analysis_toolbox/statistics/histogram.py
open_worm_analysis_toolbox/statistics/histogram_manager.py
open_worm_analysis_toolbox/statistics/pathplot.py
open_worm_analysis_toolbox/statistics/pathplot_manager.py
open_worm_analysis_toolbox/statistics/specifications.py
open_worm_analysis_toolbox/statistics/statistics_manager.py
open_worm_analysis_toolbox/statistics/feature_metadata/__init__.py
open_worm_analysis_toolbox-3.1.2.dist-info/METADATA
open_worm_analysis_toolbox-3.1.2.dist-info/RECORD
open_worm_analysis_toolbox-3.1.2.dist-info/WHEEL
open_worm_analysis_toolbox-3.1.2.dist-info/top_level.txt
