Metadata-Version: 2.1
Name: open-worm-analysis-toolbox
Version: 3.1.2
Summary: Open Worm Analysis Toolbox
Home-page: https://github.com/openworm/open-worm-analysis-toolbox
Author: Yemini, E; Jucikas, T; Schafer, W; Brown, A; Hokanson, J; Currie, M; Javer, A; OpenWorm
Author-email: mcurrie@openworm.org
License: MIT
Keywords: C. elegans worm tracking
Platform: UNKNOWN
Classifier: Development Status :: 3 - Alpha
Classifier: Intended Audience :: Science/Research
Classifier: Topic :: Scientific/Engineering :: Bio-Informatics
Classifier: License :: OSI Approved :: MIT License
Classifier: Programming Language :: Python :: 2
Classifier: Programming Language :: Python :: 2.7
Classifier: Programming Language :: Python :: 3
Classifier: Programming Language :: Python :: 3.3
Classifier: Programming Language :: Python :: 3.4
Classifier: Programming Language :: Python :: 3.5
Requires-Dist: atlas
Requires-Dist: nose
Requires-Dist: pandas
Requires-Dist: statsmodels
Requires-Dist: h5py
Requires-Dist: seaborn
